{"athlete": {"id": "364582", "uid": "s:600~a:364582", "guid": "c0f3a063-237e-3f6f-b73a-2bb7bbd51bab", "type": "soccer", "firstName": "Ignacio", "lastName": "Ferri Julià", "displayName": "Nacho Ferri", "fullName": "Nacho Ferri", "jersey": "90", "links": [{"language": "en", "rel": ["playercard", "desktop", "athlete"], "href": "https://www.espn.com/soccer/player/_/id/364582/nacho-ferri", "text": "Player Card", "shortText": "Player Card", "isExternal": false, "isPremium": false}, {"language": "en", "rel": ["stats", "desktop", "athlete"], "href": "https://www.espn.com/soccer/player/stats/_/id/364582/nacho-ferri", "text": "Stats", "shortText": "Stats", "isExternal": false, "isPremium": false}, {"language": "en", "rel": ["splits", "desktop", "athlete"], "href": "https://www.espn.com/soccer/player/splits/_/id/364582/nacho-ferri", "text": "Splits", "shortText": "Splits", "isExternal": false, "isPremium": false}, {"language": "en", "rel": ["gamelog", "desktop", "athlete"], "href": "https://www.espn.com/soccer/player/matches/_/id/364582/nacho-ferri", "text": "Matches", "shortText": "Matches", "isExternal": false, "isPremium": false}, {"language": "en", "rel": ["news", "desktop", "athlete"], "href": "https://www.espn.com/soccer/player/news/_/id/364582/nacho-ferri", "text": "News", "shortText": "News", "isExternal": false, "isPremium": false}, {"language": "en", "rel": ["bio", "desktop", "athlete"], "href": "https://www.espn.com/soccer/player/bio/_/id/364582/nacho-ferri", "text": "Bio", "shortText": "Bio", "isExternal": false, "isPremium": false}, {"language": "en", "rel": ["overview", "desktop", "athlete"], "href": "https://www.espn.com/soccer/player/_/id/364582/nacho-ferri", "text": "Overview", "shortText": "Overview", "isExternal": false, "isPremium": false}, {"language": "en", "rel": ["transfers", "desktop", "athlete"], "href": "https://www.espn.com/soccer/player/transfers/_/id/364582/nacho-ferri", "text": "Transfers", "shortText": "Transfers", "isExternal": false, "isPremium": false}, {"language": "en", "rel": ["transfers", "mobile", "athlete"], "href": "https://www.espn.com/soccer/player/transfers/_/id/364582/nacho-ferri", "text": "Transfers", "shortText": "Transfers", "isExternal": false, "isPremium": false}], "position": {"id": "19", "name": "Forward", "displayName": "Forward", "abbreviation": "F", "leaf": true, "slug": "forward"}, "team": {"id": "606", "uid": "s:600~t:606", "guid": "9485a4e3-f620-48df-2496-d674b73e224b", "slug": "bel.kvc_westerlo", "location": "KVC Westerlo", "name": "KVC Westerlo", "abbreviation": "KVCW", "displayName": "KVC Westerlo", "shortDisplayName": "Westerlo", "color": "005bd2", "alternateColor": "fffb00", "isActive": true, "isAllStar": false, "logos": [{"href": "https://a.espncdn.com/i/teamlogos/soccer/500/606.png", "width": 500, "height": 500, "rel": ["full", "default"]}, {"href": "https://a.espncdn.com/i/teamlogos/soccer/500-dark/606.png", "width": 500, "height": 500, "rel": ["full", "dark"]}], "links": [{"language": "en", "rel": ["clubhouse", "desktop", "team"], "href": "https://www.espn.com/football/club/_/id/606/kvc-westerlo", "text": "Clubhouse", "shortText": "Clubhouse", "isExternal": false, "isPremium": false}, {"language": "en", "rel": ["stats", "desktop", "team"], "href": "https://www.espn.com/soccer/team/stats/_/id/606/kvc-westerlo", "text": "Stats", "shortText": "Stats", "isExternal": false, "isPremium": false}, {"language": "en", "rel": ["schedule", "desktop", "team"], "href": "https://www.espn.com/soccer/team/fixtures/_/id/606/kvc-westerlo", "text": "Fixtures", "shortText": "Fixtures", "isExternal": false, "isPremium": false}, {"language": "en", "rel": ["results", "desktop", "team"], "href": "https://www.espn.com/soccer/team/results/_/id/606/kvc-westerlo", "text": "Results", "shortText": "Results", "isExternal": false, "isPremium": false}, {"language": "en", "rel": ["standings", "desktop", "team"], "href": "https://www.espn.com/soccer/standings/_/league/bel.1", "text": "Standings", "shortText": "Standings", "isExternal": false, "isPremium": false}, {"language": "en", "rel": ["squad", "desktop", "team"], "href": "https://www.espn.com/soccer/team/squad/_/id/606/kvc-westerlo", "text": "Squad", "shortText": "Squad", "isExternal": false, "isPremium": false}], "groups": {"uid": "s:600~l:3901", "id": "6", "name": "Belgian Pro League", "abbreviation": "Belgian Pro League", "season": {}}, "venue": {"id": "6654", "fullName": "Het Kuipje", "shortName": "Het Kuipje", "address": {"city": "Westerlo", "country": "Belgium"}}, "record": {}, "defaultLeague": {}, "isNational": false, "athletes": {}, "franchise": {}}, "active": true, "status": {"id": "1", "name": "Active", "type": "active", "abbreviation": "Active"}, "statsSummary": {"displayName": "2025-26 Belgian Pro League Stats", "statistics": [{"name": "starts-subIns", "type": "START (SUB)", "displayName": "Starts-Substitute Appearances", "shortDisplayName": "STRT-SUBIN", "description": "The number of starts a player has made in matches.-The number of times a player has come on a sub in a match.", "abbreviation": "START (SUB)", "value": 24.0, "displayValue": "24 (2)"}, {"name": "totalGoals", "displayName": "Total Goals", "shortDisplayName": "G", "description": "The number of goals scored against the opposing team.", "abbreviation": "G", "value": 7.0, "displayValue": "7"}, {"name": "goalAssists", "displayName": "Assists", "shortDisplayName": "A", "description": "The number of assists.", "abbreviation": "A", "value": 2.0, "displayValue": "2"}, {"name": "totalShots", "displayName": "Shots", "shortDisplayName": "SH", "description": "The number of shots attempted.", "abbreviation": "SH", "value": 73.0, "displayValue": "73"}]}, "displayHeight": "6' 4\"", "displayWeight": "174 lbs", "displayDOB": "5/10/2004", "age": 21, "gender": "MALE", "displayJersey": "#90", "citizenship": "Spain", "citizenshipCountry": {"alternateId": "13", "abbreviation": "ESP"}, "flag": {"href": "https://a.espncdn.com/i/teamlogos/countries/500/esp.png", "alt": "Spain", "rel": ["country-flag"]}}, "season": {"year": 2025, "startDate": "2025-07-01T04:00:00.000+00:00", "endDate": "2026-07-01T03:59:00.000+00:00", "type": {"id": "1", "type": 13499, "name": "Regular Season", "abbreviation": "2025-26 Belgian Pro League", "slug": "regular-season", "startDate": "2025-07-01T04:00:00.000+00:00", "endDate": "2026-03-24T03:59:00.000+00:00", "hasGroups": false, "hasStandings": true, "hasLegs": false}, "types": {"count": 3, "pageIndex": 1, "pageSize": 3, "pageCount": 1, "items": [{"id": "1", "type": 13499, "name": "Regular Season", "abbreviation": "2025-26 Belgian Pro League", "slug": "regular-season", "startDate": "2025-07-01T04:00:00.000+00:00", "endDate": "2026-03-24T03:59:00.000+00:00", "hasGroups": false, "hasStandings": true, "hasLegs": false}, {"id": "2", "type": 13498, "name": "Playoff Round", "abbreviation": "Playoff Round", "slug": "playoff-round", "startDate": "2026-03-17T04:00:00.000+00:00", "endDate": "2026-07-01T03:59:00.000+00:00", "hasGroups": true, "hasStandings": true, "hasLegs": false}, {"id": "3", "type": 13497, "name": "Europa Conference Playoffs", "abbreviation": "Europa Conference Playoffs", "slug": "europa-conference-playoffs", "startDate": "2026-05-01T04:00:00.000+00:00", "endDate": "2026-07-01T03:59:00.000+00:00", "hasGroups": false, "hasStandings": false, "hasLegs": false}]}, "displayName": "2025-26 Belgian Pro League", "shortDisplayName": "2025-26 Belgian Pro League", "abbreviation": "2025-26"}, "league": {"id": "3901", "uid": "s:600~l:3901", "name": "Belgian Pro League", "abbreviation": "Belgian Pro League", "slug": "bel.1", "logos": [{"href": "https://a.espncdn.com/i/leaguelogos/soccer/500/6.png", "width": 500, "height": 500, "rel": ["full", "default"]}, {"href": "https://a.espncdn.com/i/leaguelogos/soccer/500-dark/6.png", "width": 500, "height": 500, "rel": ["full", "dark"]}], "midsizeName": "BEL.1", "shortName": "Belgian Pro League"}, "playerSwitcher": {"team": {"id": "606", "uid": "s:600~t:606", "slug": "bel.kvc_westerlo", "location": "KVC Westerlo", "alternateLocation": "KVC Westerlo", "name": "KVC Westerlo", "abbreviation": "KVCW", "displayName": "KVC Westerlo", "shortDisplayName": "Westerlo", "color": "005bd2", "alternateColor": "fffb00", "logo": "https://a.espncdn.com/i/teamlogos/soccer/500/606.png", "links": [{"language": "en", "rel": ["clubhouse", "desktop", "team"], "href": "https://www.espn.com/football/club/_/id/606/kvc-westerlo", "text": "Clubhouse", "shortText": "Clubhouse", "isExternal": false, "isPremium": false}]}, "athletes": [{"id": "266722", "uid": "s:600~a:266722", "guid": "7b27cea5-1d04-3302-742b-17b366d80aa6", "displayName": "Allahyar Sayyad", "jersey": "7", "links": [{"language": "en", "rel": ["playercard", "desktop", "athlete"], "href": "https://www.espn.com/soccer/player/_/id/266722/allahyar-sayyad", "text": "Player Card", "shortText": "Player Card", "isExternal": false, "isPremium": false}, {"language": "en", "rel": ["stats", "desktop", "athlete"], "href": "https://www.espn.com/soccer/player/stats/_/id/266722/allahyar-sayyad", "text": "Stats", "shortText": "Stats", "isExternal": false, "isPremium": false}, {"language": "en", "rel": ["splits", "desktop", "athlete"], "href": "https://www.espn.com/soccer/player/splits/_/id/266722/allahyar-sayyad", "text": "Splits", "shortText": "Splits", "isExternal": false, "isPremium": false}, {"language": "en", "rel": ["gamelog", "desktop", "athlete"], "href": "https://www.espn.com/soccer/player/matches/_/id/266722/allahyar-sayyad", "text": "Matches", "shortText": "Matches", "isExternal": false, "isPremium": false}, {"language": "en", "rel": ["news", "desktop", "athlete"], "href": "https://www.espn.com/soccer/player/news/_/id/266722/allahyar-sayyad", "text": "News", "shortText": "News", "isExternal": false, "isPremium": false}, {"language": "en", "rel": ["bio", "desktop", "athlete"], "href": "https://www.espn.com/soccer/player/bio/_/id/266722/allahyar-sayyad", "text": "Bio", "shortText": "Bio", "isExternal": false, "isPremium": false}, {"language": "en", "rel": ["overview", "desktop", "athlete"], "href": "https://www.espn.com/soccer/player/_/id/266722/allahyar-sayyad", "text": "Overview", "shortText": "Overview", "isExternal": false, "isPremium": false}, {"language": "en", "rel": ["transfers", "desktop", "athlete"], "href": "https://www.espn.com/soccer/player/transfers/_/id/266722/allahyar-sayyad", "text": "Transfers", "shortText": "Transfers", "isExternal": false, "isPremium": false}, {"language": "en", "rel": ["transfers", "mobile", "athlete"], "href": "https://www.espn.com/soccer/player/transfers/_/id/266722/allahyar-sayyad", "text": "Transfers", "shortText": "Transfers", "isExternal": false, "isPremium": false}], "position": {"id": "19", "name": "Forward", "displayName": "Forward", "abbreviation": "F", "leaf": true, "slug": "forward"}, "displayJersey": "#7"}, {"id": "313950", "uid": "s:600~a:313950", "guid": "31d15423-0c6d-350e-aaa9-11c3d487c00c", "displayName": "Fernand Gouré", "jersey": "29", "links": [{"language": "en", "rel": ["playercard", "desktop", "athlete"], "href": "https://www.espn.com/soccer/player/_/id/313950/fernand-goure", "text": "Player Card", "shortText": "Player Card", "isExternal": false, "isPremium": false}, {"language": "en", "rel": ["stats", "desktop", "athlete"], "href": "https://www.espn.com/soccer/player/stats/_/id/313950/fernand-goure", "text": "Stats", "shortText": "Stats", "isExternal": false, "isPremium": false}, {"language": "en", "rel": ["splits", "desktop", "athlete"], "href": "https://www.espn.com/soccer/player/splits/_/id/313950/fernand-goure", "text": "Splits", "shortText": "Splits", "isExternal": false, "isPremium": false}, {"language": "en", "rel": ["gamelog", "desktop", "athlete"], "href": "https://www.espn.com/soccer/player/matches/_/id/313950/fernand-goure", "text": "Matches", "shortText": "Matches", "isExternal": false, "isPremium": false}, {"language": "en", "rel": ["news", "desktop", "athlete"], "href": "https://www.espn.com/soccer/player/news/_/id/313950/fernand-goure", "text": "News", "shortText": "News", "isExternal": false, "isPremium": false}, {"language": "en", "rel": ["bio", "desktop", "athlete"], "href": "https://www.espn.com/soccer/player/bio/_/id/313950/fernand-goure", "text": "Bio", "shortText": "Bio", "isExternal": false, "isPremium": false}, {"language": "en", "rel": ["overview", "desktop", "athlete"], "href": "https://www.espn.com/soccer/player/_/id/313950/fernand-goure", "text": "Overview", "shortText": "Overview", "isExternal": false, "isPremium": false}, {"language": "en", "rel": ["transfers", "desktop", "athlete"], "href": "https://www.espn.com/soccer/player/transfers/_/id/313950/fernand-goure", "text": "Transfers", "shortText": "Transfers", "isExternal": false, "isPremium": false}, {"language": "en", "rel": ["transfers", "mobile", "athlete"], "href": "https://www.espn.com/soccer/player/transfers/_/id/313950/fernand-goure", "text": "Transfers", "shortText": "Transfers", "isExternal": false, "isPremium": false}], "position": {"id": "19", "name": "Forward", "displayName": "Forward", "abbreviation": "F", "leaf": true, "slug": "forward"}, "displayJersey": "#29"}, {"id": "317076", "uid": "s:600~a:317076", "guid": "f8ac7dda-a90d-38e1-b2b3-cc7cbb57d736", "displayName": "Enis Destan", "links": [{"language": "en", "rel": ["playercard", "desktop", "athlete"], "href": "https://www.espn.com/soccer/player/_/id/317076/enis-destan", "text": "Player Card", "shortText": "Player Card", "isExternal": false, "isPremium": false}, {"language": "en", "rel": ["stats", "desktop", "athlete"], "href": "https://www.espn.com/soccer/player/stats/_/id/317076/enis-destan", "text": "Stats", "shortText": "Stats", "isExternal": false, "isPremium": false}, {"language": "en", "rel": ["splits", "desktop", "athlete"], "href": "https://www.espn.com/soccer/player/splits/_/id/317076/enis-destan", "text": "Splits", "shortText": "Splits", "isExternal": false, "isPremium": false}, {"language": "en", "rel": ["gamelog", "desktop", "athlete"], "href": "https://www.espn.com/soccer/player/matches/_/id/317076/enis-destan", "text": "Matches", "shortText": "Matches", "isExternal": false, "isPremium": false}, {"language": "en", "rel": ["news", "desktop", "athlete"], "href": "https://www.espn.com/soccer/player/news/_/id/317076/enis-destan", "text": "News", "shortText": "News", "isExternal": false, "isPremium": false}, {"language": "en", "rel": ["bio", "desktop", "athlete"], "href": "https://www.espn.com/soccer/player/bio/_/id/317076/enis-destan", "text": "Bio", "shortText": "Bio", "isExternal": false, "isPremium": false}, {"language": "en", "rel": ["overview", "desktop", "athlete"], "href": "https://www.espn.com/soccer/player/_/id/317076/enis-destan", "text": "Overview", "shortText": "Overview", "isExternal": false, "isPremium": false}, {"language": "en", "rel": ["transfers", "desktop", "athlete"], "href": "https://www.espn.com/soccer/player/transfers/_/id/317076/enis-destan", "text": "Transfers", "shortText": "Transfers", "isExternal": false, "isPremium": false}, {"language": "en", "rel": ["transfers", "mobile", "athlete"], "href": "https://www.espn.com/soccer/player/transfers/_/id/317076/enis-destan", "text": "Transfers", "shortText": "Transfers", "isExternal": false, "isPremium": false}], "position": {"id": "19", "name": "Forward", "displayName": "Forward", "abbreviation": "F", "leaf": true, "slug": "forward"}}, {"id": "320563", "uid": "s:600~a:320563", "guid": "c843fdff-c616-363a-891c-46cf9ce7db1d", "displayName": "Issai Sakamoto", "jersey": "13", "links": [{"language": "en", "rel": ["playercard", "desktop", "athlete"], "href": "https://www.espn.com/soccer/player/_/id/320563/issai-sakamoto", "text": "Player Card", "shortText": "Player Card", "isExternal": false, "isPremium": false}, {"language": "en", "rel": ["stats", "desktop", "athlete"], "href": "https://www.espn.com/soccer/player/stats/_/id/320563/issai-sakamoto", "text": "Stats", "shortText": "Stats", "isExternal": false, "isPremium": false}, {"language": "en", "rel": ["splits", "desktop", "athlete"], "href": "https://www.espn.com/soccer/player/splits/_/id/320563/issai-sakamoto", "text": "Splits", "shortText": "Splits", "isExternal": false, "isPremium": false}, {"language": "en", "rel": ["gamelog", "desktop", "athlete"], "href": "https://www.espn.com/soccer/player/matches/_/id/320563/issai-sakamoto", "text": "Matches", "shortText": "Matches", "isExternal": false, "isPremium": false}, {"language": "en", "rel": ["news", "desktop", "athlete"], "href": "https://www.espn.com/soccer/player/news/_/id/320563/issai-sakamoto", "text": "News", "shortText": "News", "isExternal": false, "isPremium": false}, {"language": "en", "rel": ["bio", "desktop", "athlete"], "href": "https://www.espn.com/soccer/player/bio/_/id/320563/issai-sakamoto", "text": "Bio", "shortText": "Bio", "isExternal": false, "isPremium": false}, {"language": "en", "rel": ["overview", "desktop", "athlete"], "href": "https://www.espn.com/soccer/player/_/id/320563/issai-sakamoto", "text": "Overview", "shortText": "Overview", "isExternal": false, "isPremium": false}, {"language": "en", "rel": ["transfers", "desktop", "athlete"], "href": "https://www.espn.com/soccer/player/transfers/_/id/320563/issai-sakamoto", "text": "Transfers", "shortText": "Transfers", "isExternal": false, "isPremium": false}, {"language": "en", "rel": ["transfers", "mobile", "athlete"], "href": "https://www.espn.com/soccer/player/transfers/_/id/320563/issai-sakamoto", "text": "Transfers", "shortText": "Transfers", "isExternal": false, "isPremium": false}], "position": {"id": "19", "name": "Forward", "displayName": "Forward", "abbreviation": "F", "leaf": true, "slug": "forward"}, "displayJersey": "#13"}, {"id": "328393", "uid": "s:600~a:328393", "guid": "e0d4ebe0-42b9-31bf-9eb4-04cf553822e6", "displayName": "Josimar Alcócer", "jersey": "77", "links": [{"language": "en", "rel": ["playercard", "desktop", "athlete"], "href": "https://www.espn.com/soccer/player/_/id/328393/josimar-alcocer", "text": "Player Card", "shortText": "Player Card", "isExternal": false, "isPremium": false}, {"language": "en", "rel": ["stats", "desktop", "athlete"], "href": "https://www.espn.com/soccer/player/stats/_/id/328393/josimar-alcocer", "text": "Stats", "shortText": "Stats", "isExternal": false, "isPremium": false}, {"language": "en", "rel": ["splits", "desktop", "athlete"], "href": "https://www.espn.com/soccer/player/splits/_/id/328393/josimar-alcocer", "text": "Splits", "shortText": "Splits", "isExternal": false, "isPremium": false}, {"language": "en", "rel": ["gamelog", "desktop", "athlete"], "href": "https://www.espn.com/soccer/player/matches/_/id/328393/josimar-alcocer", "text": "Matches", "shortText": "Matches", "isExternal": false, "isPremium": false}, {"language": "en", "rel": ["news", "desktop", "athlete"], "href": "https://www.espn.com/soccer/player/news/_/id/328393/josimar-alcocer", "text": "News", "shortText": "News", "isExternal": false, "isPremium": false}, {"language": "en", "rel": ["bio", "desktop", "athlete"], "href": "https://www.espn.com/soccer/player/bio/_/id/328393/josimar-alcocer", "text": "Bio", "shortText": "Bio", "isExternal": false, "isPremium": false}, {"language": "en", "rel": ["overview", "desktop", "athlete"], "href": "https://www.espn.com/soccer/player/_/id/328393/josimar-alcocer", "text": "Overview", "shortText": "Overview", "isExternal": false, "isPremium": false}, {"language": "en", "rel": ["transfers", "desktop", "athlete"], "href": "https://www.espn.com/soccer/player/transfers/_/id/328393/josimar-alcocer", "text": "Transfers", "shortText": "Transfers", "isExternal": false, "isPremium": false}, {"language": "en", "rel": ["transfers", "mobile", "athlete"], "href": "https://www.espn.com/soccer/player/transfers/_/id/328393/josimar-alcocer", "text": "Transfers", "shortText": "Transfers", "isExternal": false, "isPremium": false}], "position": {"id": "19", "name": "Forward", "displayName": "Forward", "abbreviation": "F", "leaf": true, "slug": "forward"}, "displayJersey": "#77"}, {"id": "364582", "uid": "s:600~a:364582", "guid": "c0f3a063-237e-3f6f-b73a-2bb7bbd51bab", "displayName": "Nacho Ferri", "jersey": "90", "links": [{"language": "en", "rel": ["playercard", "desktop", "athlete"], "href": "https://www.espn.com/soccer/player/_/id/364582/nacho-ferri", "text": "Player Card", "shortText": "Player Card", "isExternal": false, "isPremium": false}, {"language": "en", "rel": ["stats", "desktop", "athlete"], "href": "https://www.espn.com/soccer/player/stats/_/id/364582/nacho-ferri", "text": "Stats", "shortText": "Stats", "isExternal": false, "isPremium": false}, {"language": "en", "rel": ["splits", "desktop", "athlete"], "href": "https://www.espn.com/soccer/player/splits/_/id/364582/nacho-ferri", "text": "Splits", "shortText": "Splits", "isExternal": false, "isPremium": false}, {"language": "en", "rel": ["gamelog", "desktop", "athlete"], "href": "https://www.espn.com/soccer/player/matches/_/id/364582/nacho-ferri", "text": "Matches", "shortText": "Matches", "isExternal": false, "isPremium": false}, {"language": "en", "rel": ["news", "desktop", "athlete"], "href": "https://www.espn.com/soccer/player/news/_/id/364582/nacho-ferri", "text": "News", "shortText": "News", "isExternal": false, "isPremium": false}, {"language": "en", "rel": ["bio", "desktop", "athlete"], "href": "https://www.espn.com/soccer/player/bio/_/id/364582/nacho-ferri", "text": "Bio", "shortText": "Bio", "isExternal": false, "isPremium": false}, {"language": "en", "rel": ["overview", "desktop", "athlete"], "href": "https://www.espn.com/soccer/player/_/id/364582/nacho-ferri", "text": "Overview", "shortText": "Overview", "isExternal": false, "isPremium": false}, {"language": "en", "rel": ["transfers", "desktop", "athlete"], "href": "https://www.espn.com/soccer/player/transfers/_/id/364582/nacho-ferri", "text": "Transfers", "shortText": "Transfers", "isExternal": false, "isPremium": false}, {"language": "en", "rel": ["transfers", "mobile", "athlete"], "href": "https://www.espn.com/soccer/player/transfers/_/id/364582/nacho-ferri", "text": "Transfers", "shortText": "Transfers", "isExternal": false, "isPremium": false}], "position": {"id": "19", "name": "Forward", "displayName": "Forward", "abbreviation": "F", "leaf": true, "slug": "forward"}, "displayJersey": "#90"}, {"id": "391053", "uid": "s:600~a:391053", "guid": "c8871d6f-27c6-3bce-b40d-5e49acb21634", "displayName": "Eliot Bujupi", "jersey": "9", "links": [{"language": "en", "rel": ["playercard", "desktop", "athlete"], "href": "https://www.espn.com/soccer/player/_/id/391053/eliot-bujupi", "text": "Player Card", "shortText": "Player Card", "isExternal": false, "isPremium": false}, {"language": "en", "rel": ["stats", "desktop", "athlete"], "href": "https://www.espn.com/soccer/player/stats/_/id/391053/eliot-bujupi", "text": "Stats", "shortText": "Stats", "isExternal": false, "isPremium": false}, {"language": "en", "rel": ["splits", "desktop", "athlete"], "href": "https://www.espn.com/soccer/player/splits/_/id/391053/eliot-bujupi", "text": "Splits", "shortText": "Splits", "isExternal": false, "isPremium": false}, {"language": "en", "rel": ["gamelog", "desktop", "athlete"], "href": "https://www.espn.com/soccer/player/matches/_/id/391053/eliot-bujupi", "text": "Matches", "shortText": "Matches", "isExternal": false, "isPremium": false}, {"language": "en", "rel": ["news", "desktop", "athlete"], "href": "https://www.espn.com/soccer/player/news/_/id/391053/eliot-bujupi", "text": "News", "shortText": "News", "isExternal": false, "isPremium": false}, {"language": "en", "rel": ["bio", "desktop", "athlete"], "href": "https://www.espn.com/soccer/player/bio/_/id/391053/eliot-bujupi", "text": "Bio", "shortText": "Bio", "isExternal": false, "isPremium": false}, {"language": "en", "rel": ["overview", "desktop", "athlete"], "href": "https://www.espn.com/soccer/player/_/id/391053/eliot-bujupi", "text": "Overview", "shortText": "Overview", "isExternal": false, "isPremium": false}, {"language": "en", "rel": ["transfers", "desktop", "athlete"], "href": "https://www.espn.com/soccer/player/transfers/_/id/391053/eliot-bujupi", "text": "Transfers", "shortText": "Transfers", "isExternal": false, "isPremium": false}, {"language": "en", "rel": ["transfers", "mobile", "athlete"], "href": "https://www.espn.com/soccer/player/transfers/_/id/391053/eliot-bujupi", "text": "Transfers", "shortText": "Transfers", "isExternal": false, "isPremium": false}], "position": {"id": "19", "name": "Forward", "displayName": "Forward", "abbreviation": "F", "leaf": true, "slug": "forward"}, "displayJersey": "#9"}, {"id": "401308", "uid": "s:600~a:401308", "guid": "026c5c51-655d-3869-aa1b-715b4302ccf5", "displayName": "Afonso Patrão", "jersey": "10", "links": [{"language": "en", "rel": ["playercard", "desktop", "athlete"], "href": "https://www.espn.com/soccer/player/_/id/401308/afonso-patrao", "text": "Player Card", "shortText": "Player Card", "isExternal": false, "isPremium": false}, {"language": "en", "rel": ["stats", "desktop", "athlete"], "href": "https://www.espn.com/soccer/player/stats/_/id/401308/afonso-patrao", "text": "Stats", "shortText": "Stats", "isExternal": false, "isPremium": false}, {"language": "en", "rel": ["splits", "desktop", "athlete"], "href": "https://www.espn.com/soccer/player/splits/_/id/401308/afonso-patrao", "text": "Splits", "shortText": "Splits", "isExternal": false, "isPremium": false}, {"language": "en", "rel": ["gamelog", "desktop", "athlete"], "href": "https://www.espn.com/soccer/player/matches/_/id/401308/afonso-patrao", "text": "Matches", "shortText": "Matches", "isExternal": false, "isPremium": false}, {"language": "en", "rel": ["news", "desktop", "athlete"], "href": "https://www.espn.com/soccer/player/news/_/id/401308/afonso-patrao", "text": "News", "shortText": "News", "isExternal": false, "isPremium": false}, {"language": "en", "rel": ["bio", "desktop", "athlete"], "href": "https://www.espn.com/soccer/player/bio/_/id/401308/afonso-patrao", "text": "Bio", "shortText": "Bio", "isExternal": false, "isPremium": false}, {"language": "en", "rel": ["overview", "desktop", "athlete"], "href": "https://www.espn.com/soccer/player/_/id/401308/afonso-patrao", "text": "Overview", "shortText": "Overview", "isExternal": false, "isPremium": false}, {"language": "en", "rel": ["transfers", "desktop", "athlete"], "href": "https://www.espn.com/soccer/player/transfers/_/id/401308/afonso-patrao", "text": "Transfers", "shortText": "Transfers", "isExternal": false, "isPremium": false}, {"language": "en", "rel": ["transfers", "mobile", "athlete"], "href": "https://www.espn.com/soccer/player/transfers/_/id/401308/afonso-patrao", "text": "Transfers", "shortText": "Transfers", "isExternal": false, "isPremium": false}], "position": {"id": "19", "name": "Forward", "displayName": "Forward", "abbreviation": "F", "leaf": true, "slug": "forward"}, "displayJersey": "#10"}, {"id": "411026", "uid": "s:600~a:411026", "guid": "489b9171-1b89-3a8a-8116-ad7dc1e91ebd", "displayName": "Shunsuke Saito", "jersey": "38", "links": [{"language": "en", "rel": ["playercard", "desktop", "athlete"], "href": "https://www.espn.com/soccer/player/_/id/411026/shunsuke-saito", "text": "Player Card", "shortText": "Player Card", "isExternal": false, "isPremium": false}, {"language": "en", "rel": ["stats", "desktop", "athlete"], "href": "https://www.espn.com/soccer/player/stats/_/id/411026/shunsuke-saito", "text": "Stats", "shortText": "Stats", "isExternal": false, "isPremium": false}, {"language": "en", "rel": ["splits", "desktop", "athlete"], "href": "https://www.espn.com/soccer/player/splits/_/id/411026/shunsuke-saito", "text": "Splits", "shortText": "Splits", "isExternal": false, "isPremium": false}, {"language": "en", "rel": ["gamelog", "desktop", "athlete"], "href": "https://www.espn.com/soccer/player/matches/_/id/411026/shunsuke-saito", "text": "Matches", "shortText": "Matches", "isExternal": false, "isPremium": false}, {"language": "en", "rel": ["news", "desktop", "athlete"], "href": "https://www.espn.com/soccer/player/news/_/id/411026/shunsuke-saito", "text": "News", "shortText": "News", "isExternal": false, "isPremium": false}, {"language": "en", "rel": ["bio", "desktop", "athlete"], "href": "https://www.espn.com/soccer/player/bio/_/id/411026/shunsuke-saito", "text": "Bio", "shortText": "Bio", "isExternal": false, "isPremium": false}, {"language": "en", "rel": ["overview", "desktop", "athlete"], "href": "https://www.espn.com/soccer/player/_/id/411026/shunsuke-saito", "text": "Overview", "shortText": "Overview", "isExternal": false, "isPremium": false}, {"language": "en", "rel": ["transfers", "desktop", "athlete"], "href": "https://www.espn.com/soccer/player/transfers/_/id/411026/shunsuke-saito", "text": "Transfers", "shortText": "Transfers", "isExternal": false, "isPremium": false}, {"language": "en", "rel": ["transfers", "mobile", "athlete"], "href": "https://www.espn.com/soccer/player/transfers/_/id/411026/shunsuke-saito", "text": "Transfers", "shortText": "Transfers", "isExternal": false, "isPremium": false}], "position": {"id": "19", "name": "Forward", "displayName": "Forward", "abbreviation": "F", "leaf": true, "slug": "forward"}, "displayJersey": "#38"}, {"id": "417499", "uid": "s:600~a:417499", "guid": "2eb1f2b7-3f80-3de8-bb5d-bba576f311fe", "displayName": "Naoufal Bohamdi-Kamoni", "jersey": "11", "links": [{"language": "en", "rel": ["playercard", "desktop", "athlete"], "href": "https://www.espn.com/soccer/player/_/id/417499/naoufal-bohamdi-kamoni", "text": "Player Card", "shortText": "Player Card", "isExternal": false, "isPremium": false}, {"language": "en", "rel": ["stats", "desktop", "athlete"], "href": "https://www.espn.com/soccer/player/stats/_/id/417499/naoufal-bohamdi-kamoni", "text": "Stats", "shortText": "Stats", "isExternal": false, "isPremium": false}, {"language": "en", "rel": ["splits", "desktop", "athlete"], "href": "https://www.espn.com/soccer/player/splits/_/id/417499/naoufal-bohamdi-kamoni", "text": "Splits", "shortText": "Splits", "isExternal": false, "isPremium": false}, {"language": "en", "rel": ["gamelog", "desktop", "athlete"], "href": "https://www.espn.com/soccer/player/matches/_/id/417499/naoufal-bohamdi-kamoni", "text": "Matches", "shortText": "Matches", "isExternal": false, "isPremium": false}, {"language": "en", "rel": ["news", "desktop", "athlete"], "href": "https://www.espn.com/soccer/player/news/_/id/417499/naoufal-bohamdi-kamoni", "text": "News", "shortText": "News", "isExternal": false, "isPremium": false}, {"language": "en", "rel": ["bio", "desktop", "athlete"], "href": "https://www.espn.com/soccer/player/bio/_/id/417499/naoufal-bohamdi-kamoni", "text": "Bio", "shortText": "Bio", "isExternal": false, "isPremium": false}, {"language": "en", "rel": ["overview", "desktop", "athlete"], "href": "https://www.espn.com/soccer/player/_/id/417499/naoufal-bohamdi-kamoni", "text": "Overview", "shortText": "Overview", "isExternal": false, "isPremium": false}, {"language": "en", "rel": ["transfers", "desktop", "athlete"], "href": "https://www.espn.com/soccer/player/transfers/_/id/417499/naoufal-bohamdi-kamoni", "text": "Transfers", "shortText": "Transfers", "isExternal": false, "isPremium": false}, {"language": "en", "rel": ["transfers", "mobile", "athlete"], "href": "https://www.espn.com/soccer/player/transfers/_/id/417499/naoufal-bohamdi-kamoni", "text": "Transfers", "shortText": "Transfers", "isExternal": false, "isPremium": false}], "position": {"id": "19", "name": "Forward", "displayName": "Forward", "abbreviation": "F", "leaf": true, "slug": "forward"}, "displayJersey": "#11"}], "links": [{"language": "en", "rel": ["squad", "desktop", "team"], "href": "https://www.espn.com/soccer/team/squad/_/id/606/kvc-westerlo", "text": "Squad", "shortText": "Squad", "isExternal": false, "isPremium": false}], "filters": [{"displayName": "Team", "name": "team", "value": "606", "options": [{"value": "441", "displayValue": "Anderlecht"}, {"value": "17544", "displayValue": "Antwerp"}, {"value": "3610", "displayValue": "Cercle Brugge KSV"}, {"value": "570", "displayValue": "Club Brugge"}, {"value": "7878", "displayValue": "Dender"}, {"value": "3611", "displayValue": "KAA Gent"}, {"value": "7879", "displayValue": "KV Mechelen"}, {"value": "606", "displayValue": "KVC Westerlo"}, {"value": "5579", "displayValue": "Oud-Heverlee Leuven"}, {"value": "131235", "displayValue": "RAAL La Louvière"}, {"value": "938", "displayValue": "Racing Genk"}, {"value": "3616", "displayValue": "Royal Charleroi SC"}, {"value": "936", "displayValue": "Sint-Truidense"}, {"value": "559", "displayValue": "Standard Liege"}, {"value": "5807", "displayValue": "Union St.-Gilloise"}, {"value": "4691", "displayValue": "Zulte-Waregem"}]}, {"displayName": "Position", "name": "position", "value": "19", "options": [{"value": "19", "displayValue": "Forward"}, {"value": "10", "displayValue": "Midfielder"}, {"value": "2", "displayValue": "Defender"}, {"value": "1", "displayValue": "Goalkeeper"}]}]}, "quicklinks": [{"text": "[team] Quick Links", "title": "Player Quick Links - Team - Soccer - EN", "items": [{"title": "Player Quick Link - Soccer - Schedule - EN", "links": [{"href": "http://www.espn.com/soccer/team/fixture/_/id/[id]", "text": "Schedule", "shortText": "Schedule", "isExternal": false, "isPremium": false, "attributes": {"icon": "calendar"}}]}, {"title": "Player Quick Link - Soccer - Squad - EN", "links": [{"href": "http://www.espn.com/soccer/team/squad/_/id/[id]", "text": "Squad", "shortText": "Squad", "isExternal": false, "isPremium": false, "attributes": {"icon": "list__ordered_solid"}}]}, {"title": "Player Quick Link - Soccer - Stats - EN", "links": [{"href": "http://www.espn.com/soccer/team/stats/_/id/[id]", "text": "Stats", "shortText": "Stats", "isExternal": false, "isPremium": false, "attributes": {"icon": "stats"}}]}]}, {"text": "[leagueName] Quick Links", "title": "Player Quick Links - League - Soccer - EN", "items": [{"title": "Player Quick Link - Scores - Soccer - EN", "links": [{"href": "https://www.espn.com/soccer/scoreboard/_/league/[leagueAbbrev]", "text": "Scores", "shortText": "Scores", "isExternal": false, "isPremium": false, "attributes": {"icon": "scores__outline"}}]}, {"title": "Player Quick Link - Schedule - Soccer - EN", "links": [{"href": "https://www.espn.com/soccer/fixtures/_/league/[leagueAbbrev]", "text": "Schedule", "shortText": "Schedule", "isExternal": false, "isPremium": false, "attributes": {"icon": "calendar"}}]}, {"title": "Player Quick Link - Table - Soccer - EN", "links": [{"href": "http://www.espn.com/soccer/standings/_/league/[leagueAbbrev]", "text": "Table", "shortText": "Table", "isExternal": false, "isPremium": false, "attributes": {"icon": "list__ordered_solid"}}]}]}], "links": [{"language": "en", "rel": ["overview", "desktop", "athlete"], "href": "https://www.espn.com/soccer/player/_/id/364582/nacho-ferri", "text": "Overview", "shortText": "Overview", "isExternal": false, "isPremium": false}, {"language": "en", "rel": ["bio", "desktop", "athlete"], "href": "https://www.espn.com/soccer/player/bio/_/id/364582/nacho-ferri", "text": "Bio", "shortText": "Bio", "isExternal": false, "isPremium": false}, {"language": "en", "rel": ["news", "desktop", "athlete"], "href": "https://www.espn.com/soccer/player/news/_/id/364582/nacho-ferri", "text": "News", "shortText": "News", "isExternal": false, "isPremium": false}, {"language": "en", "rel": ["gamelog", "desktop", "athlete"], "href": "https://www.espn.com/soccer/player/matches/_/id/364582/nacho-ferri", "text": "Matches", "shortText": "Matches", "isExternal": false, "isPremium": false}, {"language": "en", "rel": ["stats", "desktop", "athlete"], "href": "https://www.espn.com/soccer/player/stats/_/id/364582/nacho-ferri", "text": "Stats", "shortText": "Stats", "isExternal": false, "isPremium": false}], "videos": [{"source": "espn", "id": 38815194, "headline": "FC Union Berlin vs. Eintracht Frankfurt - Game Highlights", "title": "FC Union Berlin vs. Eintracht Frankfurt - Game Highlights", "caption": "Watch the Game Highlights from FC Union Berlin vs. Eintracht Frankfurt, 11/04/2023", "description": "Watch the Game Highlights from FC Union Berlin vs. Eintracht Frankfurt, 11/04/2023", "premium": false, "ad": {"sport": "Soccer", "bundle": "sportscenter"}, "tracking": {"sportName": "Soccer", "leagueName": "German Bundesliga", "coverageType": "OnePlay", "trackingName": "SOC_One-Play (FC Union Berlin vs. Eintracht Frankfurt - Game Highlights) 2023/11/04 ESHEET", "trackingId": "dm_20231104_SOC_fc_union_berlin_vs_eintracht_frankfurt_game_highlights"}, "cerebroId": "654671a2ca84b7597a033d1b", "lastModified": "2023-11-04T16:32:27.000+00:00", "originalPublishDate": "2023-11-04T16:30:22.000+00:00", "timeRestrictions": {"embargoDate": "2023-11-04T16:30:22.000+00:00", "expirationDate": "2026-07-01T04:00:00.000+00:00"}, "deviceRestrictions": {"type": "whitelist", "devices": ["desktop", "ipad", "settop", "handset", "tablet"]}, "geoRestrictions": {"type": "whitelist", "countries": ["US", "AS", "GU", "MP", "PR", "VI", "UM"]}, "syndicatable": true, "duration": 116, "categories": [{"uid": "s:600~l:720~e:677667", "description": "Eintracht Frankfurt @ 1. FC Union Berlin", "type": "event"}, {"id": 142493, "uid": "s:600~t:125", "description": "Eintracht Frankfurt", "type": "team", "sportId": 600, "team": {"id": 125, "links": {"web": {"teams": {"href": "https://www.espn.com/soccer/club/_/id/125/eintracht-frankfurt"}}, "mobile": {"teams": {"href": "https://www.espn.com/soccer/club/_/id/125/eintracht-frankfurt"}}}}}, {"id": 192494, "uid": "s:600~t:598", "description": "1. FC Union Berlin", "type": "team", "sportId": 600, "team": {"id": 598, "links": {"web": {"teams": {"href": "https://www.espn.com/soccer/club/_/id/598/1-fc-union-berlin"}}, "mobile": {"teams": {"href": "https://www.espn.com/soccer/club/_/id/598/1-fc-union-berlin"}}}}}, {"id": 463507, "uid": "s:600~a:301047", "description": "David Datro Fofana", "type": "athlete", "sportId": 600, "athleteId": 301047, "athlete": {"id": 301047, "links": {"web": {"athletes": {"href": "https://www.espn.com/soccer/player/_/id/301047/david-datro-fofana"}}, "mobile": {"athletes": {"href": "https://www.espn.com/soccer/player/_/id/301047/david-datro-fofana"}}}}}, {"id": 436497, "uid": "s:600~a:303745", "description": "Omar Marmoush", "type": "athlete", "sportId": 600, "athleteId": 303745, "athlete": {"id": 303745, "links": {"web": {"athletes": {"href": "https://www.espn.com/soccer/player/_/id/303745/omar-marmoush"}}, "mobile": {"athletes": {"href": "https://www.espn.com/soccer/player/_/id/303745/omar-marmoush"}}}}}, {"id": 137790, "uid": "s:600~l:720", "description": "German Bundesliga", "type": "league", "sportId": 600, "leagueId": 10, "league": {"id": 720, "abbreviation": "Bundesliga", "links": {"web": {}, "mobile": {}}}}, {"id": 604158, "uid": "s:600~a:364582", "description": "Nacho Ferri", "type": "athlete", "sportId": 600, "athleteId": 364582, "athlete": {"id": 364582, "links": {"web": {"athletes": {"href": "https://www.espn.com/soccer/player/_/id/364582/nacho-ferri"}}, "mobile": {"athletes": {"href": "https://www.espn.com/soccer/player/_/id/364582/nacho-ferri"}}}}}, {"id": 81497, "uid": "s:600", "description": "Soccer", "type": "league", "sportId": 600, "leagueId": 600, "league": {"id": 600, "links": {"web": {}, "mobile": {}}}}, {"type": "guid"}, {"type": "guid"}, {"type": "guid"}, {"type": "guid"}, {"type": "guid"}, {"type": "guid"}, {"type": "guid"}, {"type": "guid"}], "posterImages": {"square": {"href": "https://media.video-cdn.espn.com/motion/2023/1104/ss_20231104_123028212_2383328/ss_20231104_123028212_2383328_1x1.jpg"}, "default": {"href": "https://media.video-cdn.espn.com/motion/2023/1104/ss_20231104_123028212_2383328/ss_20231104_123028212_2383328_default.jpg", "width": 576, "height": 324}, "wide": {"href": "https://media.video-cdn.espn.com/motion/2023/1104/ss_20231104_123028212_2383328/ss_20231104_123028212_2383328_5x2.jpg"}, "full": {"href": "https://media.video-cdn.espn.com/motion/2023/1104/ss_20231104_123028212_2383328/ss_20231104_123028212_2383328.jpg"}}, "images": [{"width": 576, "height": 324, "url": "https://media.video-cdn.espn.com/images/2023/1104/ss_20231104_123028212_2383328/ss_20231104_123028212_2383328.jpg", "name": "Poster Image"}], "thumbnail": "https://a.espncdn.com/media/motion/2023/1104/ss_20231104_123028212_2383328/ss_20231104_123028212_2383328.jpg", "links": {"sportscenter": {"href": "sportscenter://x-callback-url/showVideo?videoID=38815194&videoDSI=8310d49be4d50"}, "web": {"href": "https://www.espn.com/video/clip?id=38815194", "self": {"href": "https://www.espn.com/video/clip?id=38815194"}}, "mobile": {"href": "https://watch.auth.api.espn.com/video/auth/brightcove/386dcd93-bd5e-4506-be1c-138d11797d27/asset?UMADPARAMreferer=http://www.espn.com/video/clip?id=38815194", "alert": {"href": "https://m.espn.com/general/video/videoAlert?vid=38815194"}, "progressiveDownload": {"href": "https://watch.auth.api.espn.com/video/auth/brightcove/386dcd93-bd5e-4506-be1c-138d11797d27/asset?UMADPARAMreferer=http://www.espn.com/video/clip?id=38815194"}, "source": {"href": "https://media.video-cdn.espn.com/motion/2023/1104/ss_20231104_123028212_2383328/ss_20231104_123028212_2383328.mp4"}, "streaming": {"href": "https://watch.auth.api.espn.com/video/auth/brightcove/386dcd93-bd5e-4506-be1c-138d11797d27/asset?UMADPARAMreferer=http://www.espn.com/video/clip?id=38815194"}}, "api": {"artwork": {"href": "https://artwork.api.espn.com/artwork/collections/media/386dcd93-bd5e-4506-be1c-138d11797d27"}, "self": {"href": "https://content.core.api.espn.com/v1/video/clips/38815194"}}, "source": {"href": "https://media.video-cdn.espn.com/motion/2023/1104/ss_20231104_123028212_2383328/ss_20231104_123028212_2383328_360p30_1464k.mp4", "flash": {"href": "https://media.video-cdn.espn.com/motion/2023/1104/ss_20231104_123028212_2383328/ss_20231104_123028212_2383328.smil"}, "full": {"href": "https://media.video-cdn.espn.com/motion/2023/1104/ss_20231104_123028212_2383328/ss_20231104_123028212_2383328_360p30_1464k.mp4"}, "hds": {"href": "https://hds.video-cdn.espn.com/z/motion/2023/1104/ss_20231104_123028212_2383328/ss_20231104_123028212_2383328_rel.smil/manifest.f4m"}, "mezzanine": {"href": "https://media.video-origin.espn.com/espnvideo/2023/1104/ss_20231104_123028212_2383328/ss_20231104_123028212_2383328.mp4"}, "HD": {"href": "https://media.video-cdn.espn.com/motion/2023/1104/ss_20231104_123028212_2383328/ss_20231104_123028212_2383328_720p30_2896k.mp4"}, "HLS": {"href": "https://service-pkgespn.akamaized.net/opp/hls/espn/2023/1104/ss_20231104_123028212_2383328/ss_20231104_123028212_2383328/playlist.m3u8", "HD": {"href": "https://service-pkgespn.akamaized.net/opp/hls/espn/2023/1104/ss_20231104_123028212_2383328/ss_20231104_123028212_2383328/playlist.m3u8"}}}}}]}